with_ai_agents/client.py
with_ai_agents/llm/agents.py
with_ai_agents/llm/llms/__init__.py
with_ai_agents/llm/llms/base.py
with_ai_agents/llm/llms/dashscope.py
with_ai_agents/llm/llms/glm.py
with_ai_agents/llm/llms/openai.py
with_ai_agents/llm/services.py
with_ai_agents/llm/utils/__init__.py
with_ai_agents/llm/utils/prompts.py
with_ai_agents/llm/utils/retrievers.py
with_ai_agents-0.2.1.dist-info/METADATA
with_ai_agents-0.2.1.dist-info/WHEEL
with_ai_agents-0.2.1.dist-info/RECORD
