Metadata-Version: 2.1
Name: with-ai-agents
Version: 0.2.1
Summary: With-AI-Agents 是一个基于基本原理实现的 AI Agents（智能体），拥有联网搜索能力、页面内容提取并学习回答等功能
License: MIT
Author: yejue
Author-email: 1145331931@qq.com
Requires-Python: >=3.10,<4.0
Classifier: License :: OSI Approved :: MIT License
Classifier: Programming Language :: Python :: 3
Classifier: Programming Language :: Python :: 3.10
Classifier: Programming Language :: Python :: 3.11
Classifier: Programming Language :: Python :: 3.12
Requires-Dist: beautifulsoup4
Requires-Dist: httpx (>=0.20.0)
Requires-Dist: pydantic (>=2.0)
Project-URL: homepage, https://github.com/yejue/with-ai-agents
Project-URL: repository, https://github.com/yejue/with-ai-agents
